cybersec_scanner/__init__.py
cybersec_scanner/base_analyzer.py
cybersec_scanner/broken_access_analyzer.py
cybersec_scanner/cli.py
cybersec_scanner/design_analyser.py
cybersec_scanner/injection_analyzer.py
cybersec_scanner/prompts.py
cybersec_scanner/pydantic_models.py
cybersec_scanner/scanner.py
cybersec_scanner/secret_analyzer.py
cybersec_scanner/security_misconfig_analyzer.py
mamoguard-0.1.2.dist-info/METADATA
mamoguard-0.1.2.dist-info/WHEEL
mamoguard-0.1.2.dist-info/entry_points.txt
mamoguard-0.1.2.dist-info/top_level.txt
mamoguard-0.1.2.dist-info/RECORD
