Metadata-Version: 2.4
Name: mamoguard
Version: 0.1.2
Requires-Dist: click>=8.0
Requires-Dist: gitpython>=3.1.0
Requires-Dist: pydantic>=2.0
Requires-Dist: langchain-openai>=1.0.0
Requires-Dist: python-dotenv>=1.0
Dynamic: requires-dist
